graphragkm/__init__.py
graphragkm/cli.py
graphragkm/config/__init__.py
graphragkm/config/config.py
graphragkm/inference_processor.py
graphragkm/knowledge_enricher.py
graphragkm/main.py
graphragkm/markdown_processor.py
graphragkm/owl_generator.py
graphragkm/pdf_processor.py
graphragkm/uml_generator.py
graphragkm-0.2.0.dist-info/LICENSE
graphragkm-0.2.0.dist-info/METADATA
graphragkm-0.2.0.dist-info/WHEEL
graphragkm-0.2.0.dist-info/entry_points.txt
graphragkm-0.2.0.dist-info/RECORD
