Metadata-Version: 2.3
Name: GraphragKM
Version: 0.2.0
Summary: GraphRAG-driven AI Ontology Generation Tool
License: MIT
Requires-Python: ==3.11.*
Classifier: License :: OSI Approved :: MIT License
Classifier: Programming Language :: Python :: 3
Classifier: Programming Language :: Python :: 3.11
Requires-Dist: click (>=8.1.8,<9.0.0)
Requires-Dist: easyocr (>=1.7.2,<2.0.0)
Requires-Dist: faiss-cpu (>=1.11.0,<2.0.0)
Requires-Dist: graphrag (>=2.0.0,<3.0.0)
Requires-Dist: matplotlib (>=3.10.1,<4.0.0)
Requires-Dist: networkx (>=3.4.2,<4.0.0)
Requires-Dist: numpy (>=1.26.4,<2.0.0)
Requires-Dist: openai (>=1.65.4,<2.0.0)
Requires-Dist: opencv-python-headless (>=4.11.0.86,<5.0.0.0)
Requires-Dist: owlready2 (>=0.47,<0.48)
Requires-Dist: pandas (>=2.2.3,<3.0.0)
Requires-Dist: pathlib (>=1.0.1,<2.0.0)
Requires-Dist: pillow (>=11.1.0,<12.0.0)
Requires-Dist: pykeen (>=1.11.1,<2.0.0)
Requires-Dist: pytesseract (>=0.3.13)
Requires-Dist: pyyaml (>=6.0.2,<7.0.0)
Requires-Dist: rdflib (>=7.1.3,<8.0.0)
Requires-Dist: requests (>=2.32.3,<3.0.0)
Requires-Dist: rich (>=13.9.4,<14.0.0)
Requires-Dist: scikit-learn (>=1.6.1,<2.0.0)
Requires-Dist: sentence-transformers (>=4.1.0,<5.0.0)
